ophyd/__init__.py
ophyd/__main__.py
ophyd/_caproto_shim.py
ophyd/_dispatch.py
ophyd/_dummy_shim.py
ophyd/_pyepics_shim.py
ophyd/_version.py
ophyd/callbacks.py
ophyd/device.py
ophyd/epics_motor.py
ophyd/flyers.py
ophyd/log.py
ophyd/mca.py
ophyd/mixins.py
ophyd/ophydobj.py
ophyd/positioner.py
ophyd/pseudopos.py
ophyd/pv_positioner.py
ophyd/quadem.py
ophyd/scaler.py
ophyd/signal.py
ophyd/sim.py
ophyd/status.py
ophyd/units.py
ophyd/areadetector/__init__.py
ophyd/areadetector/base.py
ophyd/areadetector/cam.py
ophyd/areadetector/common_plugins.py
ophyd/areadetector/detectors.py
ophyd/areadetector/docs.py
ophyd/areadetector/filestore_mixins.py
ophyd/areadetector/paths.py
ophyd/areadetector/plugins.py
ophyd/areadetector/trigger_mixins.py
ophyd/areadetector/util.py
ophyd/docs/__init__.py
ophyd/docs/utils.py
ophyd/docs/templates/__init__.py
ophyd/docs/templates/autosummary/__init__.py
ophyd/tests/__init__.py
ophyd/tests/config.py
ophyd/tests/conftest.py
ophyd/tests/fake_motor_ioc.py
ophyd/tests/mca_ioc.py
ophyd/tests/scaler_ioc.py
ophyd/tests/signal_ioc.py
ophyd/tests/test_areadetector.py
ophyd/tests/test_bluesky_protocols.py
ophyd/tests/test_device.py
ophyd/tests/test_docs.py
ophyd/tests/test_epicsmotor.py
ophyd/tests/test_flyers.py
ophyd/tests/test_hints.py
ophyd/tests/test_issue944.py
ophyd/tests/test_kind.py
ophyd/tests/test_log.py
ophyd/tests/test_main.py
ophyd/tests/test_mca.py
ophyd/tests/test_ophydobj.py
ophyd/tests/test_positioner.py
ophyd/tests/test_pseudopos.py
ophyd/tests/test_pvpositioner.py
ophyd/tests/test_quadem.py
ophyd/tests/test_scaler.py
ophyd/tests/test_signal.py
ophyd/tests/test_signalpositioner.py
ophyd/tests/test_sim.py
ophyd/tests/test_status.py
ophyd/tests/test_timeout.py
ophyd/tests/test_timestamps.py
ophyd/tests/test_units.py
ophyd/tests/test_utils.py
ophyd/tests/test_versioning.py
ophyd/utils/__init__.py
ophyd/utils/epics_pvs.py
ophyd/utils/errors.py
ophyd/utils/paths.py
ophyd/utils/startup.py
ophyd-1.11.0.dist-info/licenses/LICENSE
ophyd-1.11.0.dist-info/METADATA
ophyd-1.11.0.dist-info/WHEEL
ophyd-1.11.0.dist-info/entry_points.txt
ophyd-1.11.0.dist-info/top_level.txt
ophyd-1.11.0.dist-info/RECORD
