Metadata-Version: 2.4
Name: ophyd
Version: 1.11.0
Summary: Bluesky hardware abstraction with an emphasis on EPICS
Home-page: https://github.com/bluesky/ophyd
License: BSD
Classifier: License :: OSI Approved :: BSD License
Classifier: Development Status :: 5 - Production/Stable
Classifier: Programming Language :: Python :: 3.8
Classifier: Programming Language :: Python :: 3.9
Classifier: Programming Language :: Python :: 3.10
Classifier: Programming Language :: Python :: 3.11
Classifier: Programming Language :: Python :: 3.12
Classifier: Programming Language :: Python :: 3.13
Requires-Python: >=3.8
License-File: LICENSE
Requires-Dist: networkx>=2.0
Requires-Dist: numpy
Requires-Dist: opentelemetry-api
Requires-Dist: packaging
Requires-Dist: pint
Provides-Extra: dev
Requires-Dist: attrs>=19.3.0; extra == "dev"
Requires-Dist: black==22.3.0; extra == "dev"
Requires-Dist: bluesky>=1.11.0; extra == "dev"
Requires-Dist: caproto[standard]!=1.2.0,>=0.4.2rc1; extra == "dev"
Requires-Dist: pytest-codecov; extra == "dev"
Requires-Dist: databroker>=1.0.0b1; extra == "dev"
Requires-Dist: doctr; extra == "dev"
Requires-Dist: epics-pypdb; extra == "dev"
Requires-Dist: flake8; extra == "dev"
Requires-Dist: flake8-isort; extra == "dev"
Requires-Dist: h5py; extra == "dev"
Requires-Dist: inflection; extra == "dev"
Requires-Dist: ipython; extra == "dev"
Requires-Dist: ipywidgets; extra == "dev"
Requires-Dist: matplotlib; extra == "dev"
Requires-Dist: mypy; extra == "dev"
Requires-Dist: myst-parser; extra == "dev"
Requires-Dist: numpydoc; extra == "dev"
Requires-Dist: pre-commit; extra == "dev"
Requires-Dist: pydata-sphinx-theme; extra == "dev"
Requires-Dist: pyepics<3.5.7,>=3.4.2; extra == "dev"
Requires-Dist: pytest; extra == "dev"
Requires-Dist: pytest-asyncio; extra == "dev"
Requires-Dist: pytest-cov; extra == "dev"
Requires-Dist: pytest-faulthandler; extra == "dev"
Requires-Dist: pytest-rerunfailures; extra == "dev"
Requires-Dist: pytest-timeout; extra == "dev"
Requires-Dist: pipdeptree; extra == "dev"
Requires-Dist: setuptools>=64; extra == "dev"
Requires-Dist: setuptools_scm[toml]>=6.2; extra == "dev"
Requires-Dist: sphinx-autobuild; extra == "dev"
Requires-Dist: sphinx-design; extra == "dev"
Requires-Dist: tox-direct; extra == "dev"
Dynamic: license-file
